pacote_macedo/__init__.py
pacote_macedo/modulo.py
pacote_macedo-0.0.1.dist-info/LICENSE
pacote_macedo-0.0.1.dist-info/METADATA
pacote_macedo-0.0.1.dist-info/WHEEL
pacote_macedo-0.0.1.dist-info/top_level.txt
pacote_macedo-0.0.1.dist-info/RECORD
