Metadata-Version: 2.1
Name: pacote-macedo
Version: 0.0.1
Summary: Pacote python para exibir número de 1 a 9
Home-page: UNKNOWN
Author: Ícaro de Oliveira Macedo
Author-email: icaro22070018@cesupa.aluno.br
License: MIT License
Keywords: Pacote
Platform: UNKNOWN
License-File: LICENSE
Requires-Dist: numpy
